aio-gitlab/__init__.py
aio-gitlab/aio_gitlab.py
aio_gitlab/__init__.py
aio_gitlab/aio_gitlab.py
aio_gitlab-0.1.1.dist-info/LICENSE
aio_gitlab-0.1.1.dist-info/METADATA
aio_gitlab-0.1.1.dist-info/WHEEL
aio_gitlab-0.1.1.dist-info/top_level.txt
aio_gitlab-0.1.1.dist-info/RECORD
