Metadata-Version: 2.1
Name: aio-gitlab
Version: 0.1.1
Summary: A module that allows for faster fetching of resources from Gitlab API using asyncio
Home-page: UNKNOWN
Author: Dominik Bucko
Author-email: dominik.bucko@pan-net.eu
License: UNKNOWN
Keywords: gitlab,asyncio,gitlab-ci,devops
Platform: UNKNOWN
Classifier: Programming Language :: Python :: 3
Classifier: Operating System :: OS Independent
Classifier: Intended Audience :: Developers
Classifier: Topic :: Software Development :: Libraries :: Python Modules
Classifier: License :: OSI Approved :: MIT License
Requires-Dist: python-gitlab (==1.6.0)
Requires-Dist: aiohttp (==3.6.2)
